ssm_tools/__init__.py
ssm_tools/common.py
ssm_tools/ec2_instance_connect.py
ssm_tools/ecs_session_cli.py
ssm_tools/resolver.py
ssm_tools/ssm_session_cli.py
ssm_tools/ssm_ssh_cli.py
ssm_tools/ssm_tunnel_agent.py
ssm_tools/ssm_tunnel_cli.py
ssm_tools/talker.py
aws_ssm_tools-2.0.1.dist-info/METADATA
aws_ssm_tools-2.0.1.dist-info/WHEEL
aws_ssm_tools-2.0.1.dist-info/entry_points.txt
aws_ssm_tools-2.0.1.dist-info/licenses/LICENSE
aws_ssm_tools-2.0.1.dist-info/RECORD
