Metadata-Version: 2.4
Name: aws-ssm-tools
Version: 2.0.1
Summary: Tools for AWS Systems Manager: ec2-session ecs-session ec2-ssh ssm-tunnel
Project-URL: Bug Tracker, https://github.com/mludvig/aws-ssm-tools/issues
Project-URL: Documentation, https://github.com/mludvig/aws-ssm-tools/blob/master/README.md
Project-URL: Source Code, https://github.com/mludvig/aws-ssm-tools
Author-email: Michael Ludvig <mludvig@logix.net.nz>
License-Expression: Apache-2.0
License-File: LICENSE
Keywords: aws,ec2-session,ec2-ssh,ecs-session,ssm,ssm-tunnel
Classifier: Development Status :: 5 - Production/Stable
Classifier: Environment :: Console
Classifier: Intended Audience :: System Administrators
Classifier: License :: OSI Approved :: Apache Software License
Classifier: Operating System :: POSIX :: Linux
Classifier: Programming Language :: Python :: 3 :: Only
Classifier: Programming Language :: Python :: 3.8
Classifier: Programming Language :: Python :: 3.9
Classifier: Programming Language :: Python :: 3.10
Classifier: Programming Language :: Python :: 3.11
Classifier: Programming Language :: Python :: 3.12
Classifier: Programming Language :: Python :: 3.13
Classifier: Topic :: System :: Networking
Classifier: Topic :: System :: Systems Administration
Requires-Python: >=3.8
Requires-Dist: boto3>=1.22.0
Requires-Dist: botocore
Requires-Dist: packaging
Requires-Dist: pexpect
Requires-Dist: simple-term-menu
Requires-Dist: tabulate
